Babel_heureka_code/__init__.py
Babel_heureka_code/_babel_basis_sprach_version.py
Babel_heureka_code/_babel_basis_verwalter.py
Babel_heureka_code/_babel_code.py
Babel_heureka_code/_babel_code_meta.py
Babel_heureka_code/_babel_verwalter.py
Babel_heureka_code/_dict_sprache.py
Babel_heureka_code/_sprach_config.py
Babel_heureka_code/exceptions.py
babel_heureka_code-0.1.3.dist-info/METADATA
babel_heureka_code-0.1.3.dist-info/WHEEL
babel_heureka_code-0.1.3.dist-info/top_level.txt
babel_heureka_code-0.1.3.dist-info/RECORD
