Metadata-Version: 2.1
Name: babel-heureka-code
Version: 0.1.3
Summary: Einfacher Versuch, verschiedene Sprachversionen einer Anwendung zu verwalten
Home-page: https://heureka-code.github.io/Babel-heureka-code/
Requires-Python: >=3.9
Provides-Extra: dev
Requires-Dist: commitizen ; extra == 'dev'
Requires-Dist: pre-commit ; extra == 'dev'
Provides-Extra: doc
Requires-Dist: sphinx ; extra == 'doc'
Provides-Extra: test
Requires-Dist: hypothesis ; extra == 'test'
